NetkillerDocbookFix1/README.md
NetkillerDocbookFix1/__init__.py
NetkillerDocbookFix1/__main__.py
NetkillerDocbookFix1/file.epub
NetkillerDocbookFix1/index.html
NetkillerDocbookFix1/css/__init__.py
NetkillerDocbookFix1/css/annotations.css
NetkillerDocbookFix1/css/main.css
NetkillerDocbookFix1/css/normalize.css
NetkillerDocbookFix1/css/popup.css
NetkillerDocbookFix1/font/__init__.py
NetkillerDocbookFix1/font/fontello.eot
NetkillerDocbookFix1/font/fontello.svg
NetkillerDocbookFix1/font/fontello.ttf
NetkillerDocbookFix1/font/fontello.woff
NetkillerDocbookFix1/img/__init__.py
NetkillerDocbookFix1/img/annotator-glyph-sprite.png
NetkillerDocbookFix1/img/annotator-icon-sprite.png
NetkillerDocbookFix1/img/apple-touch-icon.png
NetkillerDocbookFix1/img/cancelfullscreen.png
NetkillerDocbookFix1/img/close.png
NetkillerDocbookFix1/img/fullscreen.png
NetkillerDocbookFix1/img/loader.gif
NetkillerDocbookFix1/img/menu-icon.png
NetkillerDocbookFix1/img/save.png
NetkillerDocbookFix1/img/saved.png
NetkillerDocbookFix1/img/settings-s.png
NetkillerDocbookFix1/img/settings.png
NetkillerDocbookFix1/img/star.png
NetkillerDocbookFix1/js/__init__.py
NetkillerDocbookFix1/js/epub.js
NetkillerDocbookFix1/js/epub.min.js
NetkillerDocbookFix1/js/epub.min.map
NetkillerDocbookFix1/js/hooks.min.js
NetkillerDocbookFix1/js/hooks.min.map
NetkillerDocbookFix1/js/reader.js
NetkillerDocbookFix1/js/reader.js.map
NetkillerDocbookFix1/js/reader.min.js
NetkillerDocbookFix1/js/reader.min.map
NetkillerDocbookFix1/js/hooks/__init__.py
NetkillerDocbookFix1/js/hooks/extensions/__init__.py
NetkillerDocbookFix1/js/hooks/extensions/highlight.js
NetkillerDocbookFix1/js/libs/__init__.py
NetkillerDocbookFix1/js/libs/jquery.min.js
NetkillerDocbookFix1/js/libs/localforage.min.js
NetkillerDocbookFix1/js/libs/screenfull.js
NetkillerDocbookFix1/js/libs/screenfull.min.js
NetkillerDocbookFix1/js/libs/zip.min.js
NetkillerDocbookFix1/js/plugins/__init__.py
NetkillerDocbookFix1/js/plugins/hypothesis.js
netkiller_docbook_fix1-2025.3.24.1.dist-info/METADATA
netkiller_docbook_fix1-2025.3.24.1.dist-info/WHEEL
netkiller_docbook_fix1-2025.3.24.1.dist-info/entry_points.txt
netkiller_docbook_fix1-2025.3.24.1.dist-info/top_level.txt
netkiller_docbook_fix1-2025.3.24.1.dist-info/RECORD
